pyptu/__init__.py
pyptu/__main__.py
pyptu/common.py
pyptu/version.py
pyptu-2024.2.dist-info/METADATA
pyptu-2024.2.dist-info/WHEEL
pyptu-2024.2.dist-info/entry_points.txt
pyptu-2024.2.dist-info/licenses/LICENSE.txt
pyptu-2024.2.dist-info/RECORD
