Metadata-Version: 2.1
Name: pyptu
Version: 2024.2
Summary: Load PicoQuant PTU files.
Project-URL: homepage, https://gitlab.inria.fr/jrye/pyptu
Project-URL: repository, https://gitlab.inria.fr/jrye/pyptu.git
Project-URL: documentation, https://jrye.gitlabpages.inria.fr/pyptu
Project-URL: issues, https://gitlab.inria.fr/jrye/pyptu/-/issues
Author-email: Jan-Michael Rye <jan-michael.rye@inria.fr>
License: MIT License
License-File: LICENSE.txt
Classifier: Operating System :: OS Independent
Classifier: Programming Language :: Python :: 3
Requires-Python: >=3.6
Requires-Dist: numpy
Requires-Dist: pandas
